{
  "body": "eyJ0ZXN0IjoiYm9keSJ9",
  "resource": "/thermostats/",
  "path": "/thermostats/",
  "httpMethod": "GET",
  "isBase64Encoded": true,
  "queryStringParameters": {
    "foo": "bar"
  },
  "multiValueQueryStringParameters": {
    "foo": [
      "bar"
    ]
  },
  "pathParameters": {
    "proxy": "/thermostats"
  },
  "stageVariables": {
    "baz": "qux"
  },
  "headers": {
    "Accept": "text/html,application/xhtml+xml,application/xml;q=0.9,image/webp,*/*;q=0.8",
    "Accept-Encoding": "gzip, deflate, sdch",
    "Accept-Language": "en-US,en;q=0.8",
    "Cache-Control": "max-age=0",
    "CloudFront-Forwarded-Proto": "https",
    "CloudFront-Is-Desktop-Viewer": "true",
    "CloudFront-Is-Mobile-Viewer": "false",
    "CloudFront-Is-SmartTV-Viewer": "false",
    "CloudFront-Is-Tablet-Viewer": "false",
    "CloudFront-Viewer-Country": "US",
    "Host": "1234567890.execute-api.us-east-1.amazonaws.com",
    "Upgrade-Insecure-Requests": "1",
    "User-Agent": "Custom User Agent String",
    "Via": "1.1 08f323deadbeefa7af34d5feb414ce27.cloudfront.net (CloudFront)",
    "X-Amzn-Trace-Id": "Root=1-5dc86974-035ac025a456001d3ac4b6cb;Sampled=1",
    "X-Amz-Cf-Id": "cDehVQoZnx43VYQb9j2-nvCh-9z396Uhbp027Y2JvkCPNLmGJHqlaA==",
    "X-Forwarded-For": "127.0.0.1, 127.0.0.2",
    "X-Forwarded-Port": "443",
    "X-Forwarded-Proto": "https"
  },
  "multiValueHeaders": {
    "Accept": [
      "text/html,application/xhtml+xml,application/xml;q=0.9,image/webp,*/*;q=0.8"
    ],
    "Accept-Encoding": [
      "gzip, deflate, sdch"
    ],
    "Accept-Language": [
      "en-US,en;q=0.8"
    ],
    "Cache-Control": [
      "max-age=0"
    ],
    "CloudFront-Forwarded-Proto": [
      "https"
    ],
    "CloudFront-Is-Desktop-Viewer": [
      "true"
    ],
    "CloudFront-Is-Mobile-Viewer": [
      "false"
    ],
    "CloudFront-Is-SmartTV-Viewer": [
      "false"
    ],
    "CloudFront-Is-Tablet-Viewer": [
      "false"
    ],
    "CloudFront-Viewer-Country": [
      "US"
    ],
    "Host": [
      "0123456789.execute-api.us-east-1.amazonaws.com"
    ],
    "Upgrade-Insecure-Requests": [
      "1"
    ],
    "User-Agent": [
      "Custom User Agent String"
    ],
    "Via": [
      "1.1 08f323deadbeefa7af34d5feb414ce27.cloudfront.net (CloudFront)"
    ],
    "X-Amz-Cf-Id": [
      "cDehVQoZnx43VYQb9j2-nvCh-9z396Uhbp027Y2JvkCPNLmGJHqlaA=="
    ], 
    "X-Amzn-Trace-Id": [
      "Root=1-5dc86974-035ac025a456001d3ac4b6cb;Sampled=1"
    ],   
    "X-Forwarded-For": [
      "127.0.0.1, 127.0.0.2"
    ],
    "X-Forwarded-Port": [
      "443"
    ],
    "X-Forwarded-Proto": [
      "https"
    ]
  },
  "requestContext": {
    "accountId": "123456789012",
    "authorizer": {
      "claims": {
          "at_hash": "jFB4pZ3DsY_RCKEXAMPLE",
          "sub": "f1f50796-e81b-4793-9d55-6230647a0000",
          "aud": "mj9hu7v4nrmtsu12cispl3rt2",
          "email_verified": "true",
          "event_id": "ddba78de-02b9-4a30-b9ba-4d0ab6b08c00",
          "token_use": "id",
          "auth_time": "1602355121",
          "iss": "https://cognito-idp.us-east-1.amazonaws.com/us-east-1_i0DHLhpXX",
          "cognito:username": "f1f50796-e81b-4793-9d55-6230647a0000",
          "exp": "Sat Oct 10 19:38:41 UTC 2020",
          "iat": "Sat Oct 10 18:38:41 UTC 2020",
          "email": "johndoe@example.com"
      }
    },
    "resourceId": "123456",
    "stage": "prod",
    "requestId": "c6af9ac6-7b61-11e6-9a41-93e8deadbeef",
    "requestTime": "09/Apr/2015:12:34:56 +0000",
    "requestTimeEpoch": 1428582896000,
    "identity": {
      "cognitoIdentityPoolId": null,
      "accountId": null,
      "cognitoIdentityId": null,
      "caller": null,
      "accessKey": null,
      "sourceIp": "127.0.0.1",
      "cognitoAuthenticationType": null,
      "cognitoAuthenticationProvider": null,
      "userArn": null,
      "userAgent": "Custom User Agent String",
      "user": null
    },
    "path": "/thermostats",
    "resourcePath": "/thermostats",
    "httpMethod": "GET",
    "apiId": "1234567890",
    "protocol": "HTTP/1.1"
  }
}
